{
    "model": {
        "type": "fc1",
        "output_classes":1,
        "size_hidden_unit":16
    },
    "training": {
        "loss": "MSE",
        "optimizer": "adam",
        "learning_rate": 1e-5,
        "max_epoch": 80000
    },
    "Data": {
        "batch_size":16,
        "shuffle":true,
        "backup": "/home/cheurte/Documents/data/backup/",
        "columns_uwg_training":[
            "A4",
            "A5",
            "A11",
            "A13",
            "A14",
            "A19",
            "A20",
            "YI"
        ]
    },
    "visu": {
        "output": "/home/cheurte/Documents/data/output/fc_1/",
        "name_model": "model_fc_1"

    }
}
